tests/__init__.py
tests/__main__.py
tkf/__init__.py
tkf/__main__.py
tkf/private/.private
tkf/private/__init__.py
tkf/private/enhance_tk.py
tkf/pyrustic_data/backstage/data/build_report.json
tkf/pyrustic_data/backstage/hooking/build.json
tkf/pyrustic_data/backstage/hooking/init.json
tkf/pyrustic_data/backstage/hooking/release.json
tkf-0.0.4.dist-info/LICENSE
tkf-0.0.4.dist-info/METADATA
tkf-0.0.4.dist-info/WHEEL
tkf-0.0.4.dist-info/entry_points.txt
tkf-0.0.4.dist-info/top_level.txt
tkf-0.0.4.dist-info/RECORD
