Metadata-Version: 2.1
Name: tkf
Version: 0.0.4
Summary: Tkinter-based framework to build Python apps
Home-page: https://github.com/pyrustic/tkf
Author: Pyrustic Evangelist
Author-email: rusticalex@yahoo.com
Maintainer: Pyrustic Evangelist
Maintainer-email: rusticalex@yahoo.com
License: MIT
Keywords: framework,tkinter,GUI,modern,productivity,application,app,desktop-application
Platform: UNKNOWN
Classifier: Programming Language :: Python :: 3
Classifier: License :: OSI Approved :: MIT License
Classifier: Operating System :: OS Independent
Requires-Python: >=3.5
License-File: LICENSE
Requires-Dist: backstage
Requires-Dist: cyberpunk-theme
Requires-Dist: kurl
Requires-Dist: litedao
Requires-Dist: litemark
Requires-Dist: megawidget
Requires-Dist: probed
Requires-Dist: shared
Requires-Dist: subrun
Requires-Dist: suggestion
Requires-Dist: threadom
Requires-Dist: tkstyle
Requires-Dist: tkutil
Requires-Dist: viewable
Requires-Dist: winter-theme
